kitsunefetch/__init__.py
kitsunefetch/main.py
kitsunefetch/DATA/PROTEIN_NAME_MAPPINGS.txt
kitsunefetch/DATA/SKIP_LIGANDS.txt
kitsunefetch/DATA/SPECIES_MAPPINGS.txt
kitsunefetch-2.1.0.dist-info/METADATA
kitsunefetch-2.1.0.dist-info/WHEEL
kitsunefetch-2.1.0.dist-info/entry_points.txt
kitsunefetch-2.1.0.dist-info/top_level.txt
kitsunefetch-2.1.0.dist-info/RECORD
