Metadata-Version: 2.4
Name: kitsunefetch
Version: 2.1.0
Summary: 🦊 KitsuneFetch : Multi-Database Protein Query Tool using GraphQL API
Author-email: Elisa Rioual <elisa.rioual@riken.jp>
Maintainer-email: Elisa Rioual <elisa.rioual@riken.jp>
License: MIT
Project-URL: Homepage, https://github.com/ElisaRioual/KitsuneFetch
Project-URL: Repository, https://github.com/ElisaRioual/KitsuneFetch
Keywords: PDB,AlphaFold Protein Structure Database,ModelArchive,protein,structure,bioinformatics,RCSB,GraphQL,structural biology,crystallography,cryo-EM,NMR
Classifier: Development Status :: 4 - Beta
Classifier: Environment :: Console
Classifier: Intended Audience :: Science/Research
Classifier: Intended Audience :: Healthcare Industry
Classifier: Topic :: Scientific/Engineering :: Bio-Informatics
Classifier: Topic :: Scientific/Engineering :: Chemistry
Classifier: Topic :: Scientific/Engineering :: Medical Science Apps.
Classifier: License :: OSI Approved :: MIT License
Classifier: Operating System :: OS Independent
Classifier: Programming Language :: Python :: 3
Classifier: Programming Language :: Python :: 3.8
Classifier: Programming Language :: Python :: 3.9
Classifier: Programming Language :: Python :: 3.10
Classifier: Programming Language :: Python :: 3.11
Classifier: Programming Language :: Python :: 3.12
Classifier: Programming Language :: Python :: 3.13
Requires-Python: >=3.8
Requires-Dist: requests>=2.25.0
Requires-Dist: matplotlib>=3.3.0
Requires-Dist: numpy>=1.19.0
Provides-Extra: dev
Requires-Dist: pytest>=7.0.0; extra == "dev"
Requires-Dist: pytest-cov>=4.0.0; extra == "dev"
Requires-Dist: black>=23.0.0; extra == "dev"
Requires-Dist: flake8>=6.0.0; extra == "dev"
